odoo/addons/product_category_company_favorite/README.rst
odoo/addons/product_category_company_favorite/__init__.py
odoo/addons/product_category_company_favorite/__manifest__.py
odoo/addons/product_category_company_favorite/post_init_hook.py
odoo/addons/product_category_company_favorite/demo/res_company.xml
odoo/addons/product_category_company_favorite/i18n/fr.po
odoo/addons/product_category_company_favorite/i18n/it.po
odoo/addons/product_category_company_favorite/i18n/product_category_company_favorite.pot
odoo/addons/product_category_company_favorite/models/__init__.py
odoo/addons/product_category_company_favorite/models/product_category.py
odoo/addons/product_category_company_favorite/models/res_company.py
odoo/addons/product_category_company_favorite/readme/CONFIGURE.rst
odoo/addons/product_category_company_favorite/readme/CONTRIBUTORS.rst
odoo/addons/product_category_company_favorite/readme/DESCRIPTION.rst
odoo/addons/product_category_company_favorite/readme/ROADMAP.rst
odoo/addons/product_category_company_favorite/readme/USAGE.rst
odoo/addons/product_category_company_favorite/static/description/icon.png
odoo/addons/product_category_company_favorite/static/description/index.html
odoo/addons/product_category_company_favorite/static/description/product_category_tree.png
odoo/addons/product_category_company_favorite/static/description/product_form_view.png
odoo/addons/product_category_company_favorite/tests/__init__.py
odoo/addons/product_category_company_favorite/tests/test_module.py
odoo/addons/product_category_company_favorite/views/view_product_category.xml
odoo_addon_product_category_company_favorite-16.0.1.0.1.3.dist-info/METADATA
odoo_addon_product_category_company_favorite-16.0.1.0.1.3.dist-info/WHEEL
odoo_addon_product_category_company_favorite-16.0.1.0.1.3.dist-info/top_level.txt
odoo_addon_product_category_company_favorite-16.0.1.0.1.3.dist-info/RECORD
